hawkserver.py
hawk_server-0.0.12.dist-info/LICENSE
hawk_server-0.0.12.dist-info/METADATA
hawk_server-0.0.12.dist-info/WHEEL
hawk_server-0.0.12.dist-info/top_level.txt
hawk_server-0.0.12.dist-info/RECORD
