Metadata-Version: 2.1
Name: hawk-server
Version: 0.0.12
Summary: Utility function to perform the server-side of Hawk authentication
Home-page: https://github.com/uktrade/hawk-server
Author: Department for International Trade
Author-email: webops@digital.trade.gov.uk
License: UNKNOWN
Platform: UNKNOWN
Classifier: Programming Language :: Python :: 3
Classifier: License :: OSI Approved :: MIT License
Requires-Python: >=3.6.3
